MANIFEST.in
README.md
setup.cfg
setup.py
ScaleHDALSPAC/__allelecontainer.py
ScaleHDALSPAC/__backend.py
ScaleHDALSPAC/__init__.py
ScaleHDALSPAC/__main__.py
ScaleHDALSPAC/sherpa.py
ScaleHDALSPAC.egg-info/PKG-INFO
ScaleHDALSPAC.egg-info/SOURCES.txt
ScaleHDALSPAC.egg-info/dependency_links.txt
ScaleHDALSPAC.egg-info/entry_points.txt
ScaleHDALSPAC.egg-info/requires.txt
ScaleHDALSPAC.egg-info/top_level.txt
ScaleHDALSPAC/align/__alignment.py
ScaleHDALSPAC/align/__atypical.py
ScaleHDALSPAC/align/__init__.py
ScaleHDALSPAC/config/config.dtd
ScaleHDALSPAC/genHTML/__generateHTML.py
ScaleHDALSPAC/genHTML/__init__.py
ScaleHDALSPAC/genHTML/chartBase.js
ScaleHDALSPAC/genHTML/chartBoxPlot.js
ScaleHDALSPAC/genHTML/chartZoom.js
ScaleHDALSPAC/genHTML/gridism.css
ScaleHDALSPAC/genHTML/jquery.js
ScaleHDALSPAC/genHTML/msa.js
ScaleHDALSPAC/genHTML/scalehd.css
ScaleHDALSPAC/genHTML/scalehd.js
ScaleHDALSPAC/genHTML/tablefilter.js
ScaleHDALSPAC/genHTML/templates/alleletable.html
ScaleHDALSPAC/genHTML/templates/base.html
ScaleHDALSPAC/genHTML/templates/list.html
ScaleHDALSPAC/genHTML/templates/seqALN.html
ScaleHDALSPAC/genHTML/templates/seqGTYPE.html
ScaleHDALSPAC/genHTML/templates/seqqc.html
ScaleHDALSPAC/genHTML/templates/sequencedata.html
ScaleHDALSPAC/genHTML/templates/trim.html
ScaleHDALSPAC/predict/__init__.py
ScaleHDALSPAC/predict/__prediction.py
ScaleHDALSPAC/predict/__snpcalling.py
ScaleHDALSPAC/seq_qc/__init__.py
ScaleHDALSPAC/seq_qc/__quality_control.py
ScaleHDALSPAC/train/likelihood_matrix.csv
ScaleHDALSPAC/train/long_descr.rst
ScaleHDALSPAC/train/polyglutamine.csv
ScaleHDALSPAC/train/raw_matrix.csv