Metadata-Version: 1.2
Name: ScaleHDALSPAC
Version: 0.324.1
Summary: Automated DNA micro-satellite genotyping.
Home-page: https://github.com/helloabunai/ScaleHDALSPAC
Author: Alastair Maxwell/University of Glasgow
Author-email: alastair.maxwell@glasgow.ac.uk
License: GPLv3
Keywords: machine-learning genotyping bioinformatics huntington-disease
Platform: UNKNOWN
Classifier: Development Status :: 2 - Pre-Alpha
Classifier: Intended Audience :: Education
Classifier: Intended Audience :: End Users/Desktop
Classifier: Intended Audience :: Science/Research
Classifier: License :: OSI Approved :: GNU General Public License v3 (GPLv3)
Classifier: Programming Language :: Python :: 2.7
Classifier: Environment :: Console
Classifier: Operating System :: MacOS :: MacOS X
Classifier: Operating System :: POSIX
Requires-Python: >=2.7.13
